qrcodegenpy_shankonduru/__init__.py
qrcodegenpy_shankonduru/cli.py
qrcodegenpy_shankonduru/qr_generator.py
qrcodegenpy_shankonduru-1.0.0.dist-info/entry_points.txt
qrcodegenpy_shankonduru-1.0.0.dist-info/licenses/LICENSE
qrcodegenpy_shankonduru-1.0.0.dist-info/METADATA
qrcodegenpy_shankonduru-1.0.0.dist-info/WHEEL
qrcodegenpy_shankonduru-1.0.0.dist-info/RECORD
