Metadata-Version: 2.4
Name: qrcodegenpy-shankonduru
Version: 1.0.0
Summary: A comprehensive QR Code Generator library with CLI, Streamlit UI, and robust testing
License: MIT
License-File: LICENSE
Keywords: qr-code,qr-generator,barcode,python,cli,streamlit
Author: Shan Konduru
Author-email: shankonduru@gmail.com
Requires-Python: >=3.12,<4.0
Classifier: Development Status :: 5 - Production/Stable
Classifier: Intended Audience :: Developers
Classifier: License :: OSI Approved :: MIT License
Classifier: Operating System :: OS Independent
Classifier: Programming Language :: Python :: 3
Classifier: Programming Language :: Python :: 3.12
Classifier: Programming Language :: Python :: 3.13
Classifier: Programming Language :: Python :: 3.14
Classifier: Topic :: Multimedia :: Graphics
Classifier: Topic :: Software Development :: Libraries :: Python Modules
Classifier: Topic :: Utilities
Requires-Dist: pillow (>=10.2.0,<11.0.0)
Requires-Dist: qrcode (>=7.4.2,<8.0.0)
Requires-Dist: streamlit (>=1.30.0,<2.0.0)
Project-URL: Bug Tracker, https://github.com/shankonduru/qrcodegenpy/issues
Project-URL: Documentation, https://github.com/shankonduru/qrcodegenpy/blob/main/README.md
Project-URL: Homepage, https://github.com/shankonduru/qrcodegenpy
Project-URL: Repository, https://github.com/shankonduru/qrcodegenpy
Project-URL: Source Code, https://github.com/shankonduru/qrcodegenpy
